{
    "data": [
            {
                "MatNo": "DB100002", 
                "Base": "临港", 
                "库位": "LS015A011",
                "单位": "PC",
                "数量": "14",
                "批号": "D00000000000034",
                "车间码": "LPSZZ",
                "制造商": "日东",
                "MatDetail": "气动接头|Connector|80SN" 
            },
            {
                "MatNo": "DB100002", 
                "Base": "临港", 
                "库位": "LS015A012",
                "单位": "PC",
                "数量": "14",
                "批号": "D00000000000034",
                "车间码": "LPSZZ",
                "制造商": "日东",
                "MatDetail": "气动接头|Connector|80SN"
            },
            {
                "MatNo": "DB100002", 
                "Base": "临港", 
                "库位": "LS015A013",
                "单位": "PC",
                "数量": "14",
                "批号": "D00000000000034",
                "车间码": "LPSZZ",
                "制造商": "日东",
                "MatDetail": "气动接头|Connector|80SN"
            },
            {
                "MatNo": "DB100002", 
                "Base": "临港", 
                "库位": "LS015A014",
                "单位": "PC",
                "数量": "14",
                "批号": "D00000000000034",
                "车间码": "LPSZZ",
                "制造商": "日东",
                "MatDetail": "气动接头|Connector|80SN"
            },
            {
                "MatNo": "DB100002", 
                "Base": "临港", 
                "库位": "LS015A015",
                "单位": "PC",
                "数量": "14",
                "批号": "D00000000000034",
                "车间码": "LPSZZ",
                "制造商": "日东",
                "MatDetail": "气动接头|Connector|80SN"
            },
            {
                "MatNo": "DB100002",
                "Base": "临港", 
                "库位": "LS015A016",
                "单位": "PC",
                "数量": "14",
                "批号": "D00000000000034",
                "车间码": "LPSZZ",
                "制造商": "日东",
                "MatDetail": "气动接头|Connector|80SN"
            },
            {
                "MatNo": "DB100002", 
                "Base": "临港", 
                "库位": "LS015A017",
                "单位": "PC",
                "数量": "14",
                "批号": "D00000000000034",
                "车间码": "LPSZZ",
                "制造商": "日东",
                "MatDetail": "气动接头|Connector|80SN"
            },
            {
                "MatNo": "DB100002", 
                "Base": "临港", 
                "库位": "LS015A018",
                "单位": "PC",
                "数量": "14",
                "批号": "D00000000000034",
                "车间码": "LPSZZ",
                "制造商": "日东",
                "MatDetail": "气动接头|Connector|80SN"
            },
            {
                "MatNo": "DB100002", 
                "Base": "临港", 
                "库位": "LS015A019",
                "单位": "PC",
                "数量": "14",
                "批号": "D00000000000034",
                "车间码": "LPSZZ",
                "制造商": "日东",
                "MatDetail": "气动接头|Connector|80SN"
            },
            {
                "MatNo": "DB100002", 
                "Base": "临港", 
                "库位": "LS015A020",
                "单位": "PC",
                "数量": "14",
                "批号": "D00000000000034",
                "车间码": "LPSZZ",
                "制造商": "日东",
                "MatDetail": "气动接头|Connector|80SN"
            }
        ],
        "totalPages": 5
    }